kubecrds/__init__.py
kubecrds/schemabase.py
kubecrds/types.py
kubecrds-34.1.4.dist-info/METADATA
kubecrds-34.1.4.dist-info/WHEEL
kubecrds-34.1.4.dist-info/licenses/LICENSE
kubecrds-34.1.4.dist-info/licenses/NOTICE
kubecrds-34.1.4.dist-info/RECORD
