Metadata-Version: 2.4
Name: kubecrds
Version: 34.1.4
Summary: Create Kubernetes CRD using Python dataclasses
License: Apache-2.0
License-File: LICENSE
License-File: NOTICE
Author: Paris Nakita Kejser
Author-email: hi@pnk.sh
Requires-Python: >=3.11,<4
Classifier: License :: OSI Approved :: Apache Software License
Classifier: Programming Language :: Python :: 3
Classifier: Programming Language :: Python :: 3.11
Classifier: Programming Language :: Python :: 3.12
Classifier: Programming Language :: Python :: 3.13
Classifier: Programming Language :: Python :: 3.14
Requires-Dist: PyYAML (>=6.0)
Requires-Dist: apischema (>=0.19.0)
Requires-Dist: kubernetes (>=34.1.0,<35.0.0)
Project-URL: Bug Tracker, https://github.com/KubeHiveIO/kubecrd/issues
Project-URL: Repository, https://github.com/KubeHiveIO/kubecrd
